metricflow/__init__.py
metricflow/aggregation_properties.py
metricflow/assert_one_arg.py
metricflow/instances.py
metricflow/random_id.py
metricflow/visitor.py
metricflow/api/__init__.py
metricflow/api/metricflow_client.py
metricflow/cli/__init__.py
metricflow/cli/api_context.py
metricflow/cli/cli_context.py
metricflow/cli/constants.py
metricflow/cli/custom_click_types.py
metricflow/cli/main.py
metricflow/cli/tutorial.py
metricflow/cli/utils.py
metricflow/cli/dbt_connectors/__init__.py
metricflow/cli/dbt_connectors/adapter_backed_client.py
metricflow/cli/dbt_connectors/dbt_config_accessor.py
metricflow/collection_helpers/__init__.py
metricflow/collection_helpers/merger.py
metricflow/dag/__init__.py
metricflow/dag/dag_to_text.py
metricflow/dag/dag_visualization.py
metricflow/dag/id_prefix.py
metricflow/dag/mf_dag.py
metricflow/dag/sequential_id.py
metricflow/dataflow/__init__.py
metricflow/dataflow/dataflow_plan.py
metricflow/dataflow/sql_column.py
metricflow/dataflow/sql_table.py
metricflow/dataflow/builder/__init__.py
metricflow/dataflow/builder/dataflow_plan_builder.py
metricflow/dataflow/builder/measure_additiveness.py
metricflow/dataflow/builder/node_data_set.py
metricflow/dataflow/builder/node_evaluator.py
metricflow/dataflow/builder/partitions.py
metricflow/dataflow/builder/source_node.py
metricflow/dataflow/optimizer/__init__.py
metricflow/dataflow/optimizer/dataflow_plan_optimizer.py
metricflow/dataflow/optimizer/source_scan/__init__.py
metricflow/dataflow/optimizer/source_scan/cm_branch_combiner.py
metricflow/dataflow/optimizer/source_scan/matching_linkable_specs.py
metricflow/dataflow/optimizer/source_scan/source_scan_optimizer.py
metricflow/dataset/__init__.py
metricflow/dataset/convert_semantic_model.py
metricflow/dataset/dataset.py
metricflow/dataset/semantic_model_adapter.py
metricflow/dataset/sql_dataset.py
metricflow/engine/__init__.py
metricflow/engine/metricflow_engine.py
metricflow/engine/models.py
metricflow/engine/time_source.py
in_metricflow-0.205.0.dist-info/METADATA
in_metricflow-0.205.0.dist-info/WHEEL
in_metricflow-0.205.0.dist-info/entry_points.txt
in_metricflow-0.205.0.dist-info/licenses/LICENSE
in_metricflow-0.205.0.dist-info/RECORD
