Metadata-Version: 2.1
Name: in-metricflow
Version: 0.205.0
Summary: Translates a simple metric definition into reusable SQL and executes it against the SQL engine of your choice.
Project-URL: Documentation, https://transform.co/metricflow
Project-URL: Source Code, https://github.com/transform-data/metricflow
Author: dbt Labs
License-Expression: BUSL-1.1
License-File: LICENSE
Classifier: Development Status :: 4 - Beta
Classifier: Programming Language :: Python
Classifier: Programming Language :: Python :: 3.8
Classifier: Programming Language :: Python :: 3.9
Classifier: Programming Language :: Python :: 3.10
Classifier: Programming Language :: Python :: 3.11
Classifier: Programming Language :: Python :: Implementation :: CPython
Classifier: Programming Language :: Python :: Implementation :: PyPy
Requires-Python: <3.12,>=3.8
Requires-Dist: click>=7.1.2
Requires-Dist: dbt-core<1.8.0,>=1.7.0
Requires-Dist: dbt-semantic-interfaces<0.5.0,>=0.4.2
Requires-Dist: graphviz<0.21,>=0.18.2
Requires-Dist: halo<0.1.0,>=0.0.31
Requires-Dist: jinja2>=3.1.3
Requires-Dist: more-itertools<10.2.0,>=8.10.0
Requires-Dist: pandas<1.6.0,>=1.5.0
Requires-Dist: pydantic<1.11.0,>=1.10.0
Requires-Dist: python-dateutil<2.9.0,>=2.8.2
Requires-Dist: pyyaml<7.0.0,>=6.0
Requires-Dist: rapidfuzz<4.0,>=3.0
Requires-Dist: ruamel-yaml<0.18.0,>=0.17.21
Requires-Dist: tabulate>=0.8.9
Requires-Dist: typing-extensions<5.0,>=4.4
Requires-Dist: update-checker<0.19.0,>=0.18.0
Provides-Extra: dbt-bigquery
Requires-Dist: dbt-bigquery<1.8.0,>=1.7.0; extra == 'dbt-bigquery'
Provides-Extra: dbt-databricks
Requires-Dist: dbt-databricks<1.8.0,>=1.7.0; extra == 'dbt-databricks'
Provides-Extra: dbt-duckdb
Requires-Dist: dbt-duckdb<1.8.0,>=1.7.0; extra == 'dbt-duckdb'
Provides-Extra: dbt-postgres
Requires-Dist: dbt-postgres<1.8.0,>=1.7.0; extra == 'dbt-postgres'
Provides-Extra: dbt-redshift
Requires-Dist: dbt-redshift<1.8.0,>=1.7.0; extra == 'dbt-redshift'
Provides-Extra: dbt-snowflake
Requires-Dist: dbt-snowflake<1.8.0,>=1.7.0; extra == 'dbt-snowflake'
Provides-Extra: dbt-trino
Requires-Dist: dbt-trino<1.8.0,>=1.7.0; extra == 'dbt-trino'
Provides-Extra: dev-packages
Requires-Dist: click>=8.1.6; extra == 'dev-packages'
Requires-Dist: mypy<1.8.0,>=1.7.0; extra == 'dev-packages'
Requires-Dist: pre-commit<3.3.0,>=3.2.2; extra == 'dev-packages'
Requires-Dist: pytest-mock<3.8.0,>=3.7.0; extra == 'dev-packages'
Requires-Dist: pytest-xdist<3.3.0,>=3.2.1; extra == 'dev-packages'
Requires-Dist: pytest<7.2.0,>=7.1.1; extra == 'dev-packages'
Requires-Dist: types-python-dateutil; extra == 'dev-packages'
Requires-Dist: types-pyyaml; extra == 'dev-packages'
Requires-Dist: types-tabulate; extra == 'dev-packages'
Provides-Extra: sql-client-packages
Requires-Dist: sqlalchemy2-stubs<0.0.3,>=0.0.2a21; extra == 'sql-client-packages'
Requires-Dist: sqlalchemy<1.5.0,>=1.4.42; extra == 'sql-client-packages'
Provides-Extra: trino-sql-client-packages
Requires-Dist: trino<0.328.0,>=0.327.0; extra == 'trino-sql-client-packages'
